spacy_richtext_utils/__init__.py
spacy_richtext_utils/common_usage.py
spacy_richtext_utils/pipe_steps.py
spacy_richtext_utils/tokenizer.py
spacy_richtext_utils-0.1.1.dist-info/WHEEL
spacy_richtext_utils-0.1.1.dist-info/METADATA
spacy_richtext_utils-0.1.1.dist-info/RECORD
